robotmodels/__init__.py
robotmodels/albert/__init__.py
robotmodels/albert/meshes/chassis_link.STL
robotmodels/albert/meshes/chassis_link.dae
robotmodels/albert/meshes/colors.png
robotmodels/albert/meshes/extrusion.stl
robotmodels/albert/meshes/finger.mtl
robotmodels/albert/meshes/finger.obj
robotmodels/albert/meshes/finger.stl
robotmodels/albert/meshes/hand.mtl
robotmodels/albert/meshes/hand.obj
robotmodels/albert/meshes/hand.stl
robotmodels/albert/meshes/internal_link.STL
robotmodels/albert/meshes/internal_link.dae
robotmodels/albert/meshes/lift_link.STL
robotmodels/albert/meshes/lift_link.dae
robotmodels/albert/meshes/link0.dae
robotmodels/albert/meshes/link0.stl
robotmodels/albert/meshes/link1.mtl
robotmodels/albert/meshes/link1.obj
robotmodels/albert/meshes/link1.stl
robotmodels/albert/meshes/link2.mtl
robotmodels/albert/meshes/link2.obj
robotmodels/albert/meshes/link2.stl
robotmodels/albert/meshes/link3.mtl
robotmodels/albert/meshes/link3.obj
robotmodels/albert/meshes/link3.stl
robotmodels/albert/meshes/link4.mtl
robotmodels/albert/meshes/link4.obj
robotmodels/albert/meshes/link4.stl
robotmodels/albert/meshes/link5.mtl
robotmodels/albert/meshes/link5.obj
robotmodels/albert/meshes/link5.stl
robotmodels/albert/meshes/link6.mtl
robotmodels/albert/meshes/link6.obj
robotmodels/albert/meshes/link6.stl
robotmodels/albert/meshes/link7.dae
robotmodels/albert/meshes/link7.stl
robotmodels/albert/meshes/rotacastor_left_link.STL
robotmodels/albert/meshes/rotacastor_right_link.STL
robotmodels/albert/meshes/top_plate.stl
robotmodels/albert/meshes/top_plate_collision.stl
robotmodels/albert/meshes/wheel_left_link.STL
robotmodels/albert/meshes/wheel_right_link.STL
robotmodels/albert/urdf/__init__.py
robotmodels/albert/urdf/albert.urdf
robotmodels/albert/xml/__init__.py
robotmodels/aloha/__init__.py
robotmodels/aloha/aloha_scene_home.txt
robotmodels/aloha/meshes/angled_extrusion.stl
robotmodels/aloha/meshes/corner_bracket.stl
robotmodels/aloha/meshes/d405_solid.stl
robotmodels-0.2.0.dist-info/METADATA
robotmodels-0.2.0.dist-info/WHEEL
robotmodels-0.2.0.dist-info/entry_points.txt
robotmodels-0.2.0.dist-info/RECORD
