Metadata-Version: 2.3
Name: robotmodels
Version: 0.2.0
Summary: A collection of robot models
Author: Max Spahn
Author-email: m.spahn@tudelft.nl
Requires-Python: >=3.10,<4.0
Classifier: Programming Language :: Python :: 3
Classifier: Programming Language :: Python :: 3.10
Classifier: Programming Language :: Python :: 3.11
Classifier: Programming Language :: Python :: 3.12
Classifier: Programming Language :: Python :: 3.13
Requires-Dist: yourdfpy[full] (>=0.0.56,<0.0.57)
